Metadata-Version: 2.1
Name: alpaca-prov
Version: 0.2.0
Summary: Alpaca is a Python package for the capture of provenance information during the execution of Python scripts that process data.
Home-page: https://github.com/INM-6/alpaca
Author: Alpaca authors and contributors
Author-email: 
License: BSD
Classifier: Development Status :: 4 - Beta
Classifier: Intended Audience :: Science/Research
Classifier: License :: OSI Approved :: BSD License
Classifier: Natural Language :: English
Classifier: Operating System :: OS Independent
Classifier: Programming Language :: Python :: 3
Classifier: Topic :: Scientific/Engineering
License-File: LICENSE.txt
